shape_detector/__init__.py
shape_detector/main.py
shapedetector-0.0.1.dist-info/METADATA
shapedetector-0.0.1.dist-info/WHEEL
shapedetector-0.0.1.dist-info/top_level.txt
shapedetector-0.0.1.dist-info/RECORD
