Metadata-Version: 2.1
Name: shapedetector
Version: 0.0.1
Summary: Yolov5 Shape Detector
Home-page: UNKNOWN
Author: Mehdi Hosseini Moghadam
Author-email: <m.h.moghadam1996@gmail.com>
License: UNKNOWN
Keywords: python,Yolov5,Yolo,Shape Detector,shape object detection
Platform: UNKNOWN
Classifier: Development Status :: 1 - Planning
Classifier: Intended Audience :: Developers
Classifier: Programming Language :: Python :: 3
Classifier: Operating System :: Unix
Classifier: Operating System :: MacOS :: MacOS X
Classifier: Operating System :: Microsoft :: Windows
